LICENSE.rst
MANIFEST.in
README.rst
setup.cfg
setup.py
orochi_python/__init__.py
orochi_python/orochi.py
orochi_python.egg-info/PKG-INFO
orochi_python.egg-info/SOURCES.txt
orochi_python.egg-info/dependency_links.txt
orochi_python.egg-info/requires.txt
orochi_python.egg-info/top_level.txt
orochi_python/binary/orochi-0.1.1.jar